LICENSE.txt
MANIFEST.in
README
README.md
setup.py
urlrecode/__init__.py
urlrecode/main.py
urlrecode.egg-info/PKG-INFO
urlrecode.egg-info/SOURCES.txt
urlrecode.egg-info/dependency_links.txt
urlrecode.egg-info/entry_points.txt
urlrecode.egg-info/top_level.txt