Metadata-Version: 2.1
Name: urlrecode
Version: 1.0.9
Summary: Simple URLEncode and URLDecode which I needed for a couple of bash scripts.
Home-page: https://github.com/MKaterbarg/urlrecode
Author: Martijn Katerbarg
Author-email: martijnkaterbarg@gmail.com
License: MIT
Platform: UNKNOWN
License-File: LICENSE.txt
